tg_bot_screen/__init__.py
tg_bot_screen/bot_manager.py
tg_bot_screen/button_rows.py
tg_bot_screen/callback_data.py
tg_bot_screen/error_info.py
tg_bot_screen/input_callback.py
tg_bot_screen/message.py
tg_bot_screen/screen.py
tg_bot_screen/session.py
tg_bot_screen/user_data.py
tg_bot_screen/user_screen.py
tg_bot_screen/ptb/__init__.py
tg_bot_screen/ptb/bot_manager.py
tg_bot_screen/ptb/button_rows.py
tg_bot_screen/ptb/screen.py
tg_bot_screen/ptb/session.py
tg_bot_screen/ptb/user_data.py
tg_bot_screen/ptb/user_screen.py
tg_bot_screen/ptb/messages/__init__.py
tg_bot_screen/ptb/messages/audio_message.py
tg_bot_screen/ptb/messages/document_message.py
tg_bot_screen/ptb/messages/message.py
tg_bot_screen/ptb/messages/photo_message.py
tg_bot_screen/ptb/messages/simple_message.py
tg_bot_screen/ptb/messages/video_message.py
tg_bot_screen/ptb/messages/video_note_message.py
tg_bot_screen-1.4.43.dist-info/METADATA
tg_bot_screen-1.4.43.dist-info/WHEEL
tg_bot_screen-1.4.43.dist-info/licenses/LICENSE
tg_bot_screen-1.4.43.dist-info/RECORD
