Metadata-Version: 2.4
Name: tg_bot_screen
Version: 1.4.43
Summary: Lib that helps with telegram bots
Project-URL: Homepage, https://github.com/Neveix/tg_bot_base
Project-URL: Issues, https://github.com/Neveix/tg_bot_base/issues
Author-email: Neveix <i@neveix.ru>
License: MIT
License-File: LICENSE
Classifier: License :: OSI Approved :: MIT License
Classifier: Operating System :: OS Independent
Classifier: Programming Language :: Python :: 3
Requires-Python: >=3.12
Provides-Extra: ptb
Requires-Dist: python-telegram-bot[job-queue]>=21.9; extra == 'ptb'
